digiPYn/__init__.py
digiPYn/config.py
digiPYn/converter.py
digipyn-0.1.0.dist-info/licenses/LICENSE
tests/__init__.py
tests/test_converter.py
digipyn-0.1.0.dist-info/METADATA
digipyn-0.1.0.dist-info/WHEEL
digipyn-0.1.0.dist-info/top_level.txt
digipyn-0.1.0.dist-info/RECORD
